ctt.py
setup.py
ctt/__init__.py
ctt/cosign.py
ctt/filters.py
ctt/platform.py
ctt/process_dependencies.py
ctt/processing_model.py
ctt/processors.py
ctt/rbsc_bom.py
ctt/uploaders.py
ctt/util.py
ctt/test/__init__.py
ctt/test/filters_test.py
ctt/test/platform_test.py
ctt/test/process_deps_test.py
ctt/test/processors_test.py
ctt/test/uploaders_test.py
cnudie_transport_tool-0.140.0.dist-info/METADATA
cnudie_transport_tool-0.140.0.dist-info/WHEEL
cnudie_transport_tool-0.140.0.dist-info/top_level.txt
cnudie_transport_tool-0.140.0.dist-info/RECORD
