Metadata-Version: 2.1
Name: cnudie-transport-tool
Version: 0.140.0
Summary: CNUDIE Transport Tool
Requires-Python: >=3.10
Requires-Dist: gardener-cicd-libs (>=1.1871.0)
